README.md
package_info.json
setup.py
th2_grpc_hand/__init__.py
th2_grpc_hand/rhactionsmessages.proto
th2_grpc_hand/rhactionsmessages_pb2.py
th2_grpc_hand/rhactionsmessages_pb2_grpc.py
th2_grpc_hand/rhactionsmessages_win.proto
th2_grpc_hand/rhactionsmessages_win_pb2.py
th2_grpc_hand/rhactionsmessages_win_pb2_grpc.py
th2_grpc_hand/rhbatch.proto
th2_grpc_hand/rhbatch_pb2.py
th2_grpc_hand/rhbatch_pb2_grpc.py
th2_grpc_hand/rhbatch_service.py
th2_grpc_hand.egg-info/PKG-INFO
th2_grpc_hand.egg-info/SOURCES.txt
th2_grpc_hand.egg-info/dependency_links.txt
th2_grpc_hand.egg-info/requires.txt
th2_grpc_hand.egg-info/top_level.txt