Metadata-Version: 2.1
Name: th2-grpc-hand
Version: 2.1.0
Summary: th2_grpc_hand
Home-page: https://github.com/th2-net/th2-grpc-hand
Author: TH2-devs
Author-email: th2-devs@exactprosystems.com
License: Apache License 2.0
Platform: UNKNOWN
Requires-Python: >=3.7
